Metadata-Version: 2.1
Name: worldometer-scraper
Version: 1.0.0
Summary: A python library to scrape World-o-Meter
Home-page: UNKNOWN
Author: DataKund
Author-email: datakund@gmail.com
License: Apache License 2.0
Keywords: scrape worldometer world-o-meter python bot_studio automation scraper country total cases deaths per million
Platform: UNKNOWN
License-File: LICENSE
